hagi/__init__.py
hagi/_version.py
hagi/cmd.py
hagi/context.py
hagi/process.py
hagi/program.py
hagi/task.py
hagi/watcher.py
hagi-0.0.4.dist-info/LICENSE
hagi-0.0.4.dist-info/METADATA
hagi-0.0.4.dist-info/WHEEL
hagi-0.0.4.dist-info/entry_points.txt
hagi-0.0.4.dist-info/top_level.txt
hagi-0.0.4.dist-info/RECORD
