Metadata-Version: 2.1
Name: hagi
Version: 0.0.4
Author-email: Lindasy Zhou <i@lin.moe>
License: Affero General Public License GPL v3 (AGPLv3)
Project-URL: Homepage, https://sr.ht/~lindsay/faba
Classifier: Programming Language :: Python :: 3.10
Classifier: Programming Language :: Python :: 3.9
Requires-Python: >=3.7
License-File: LICENSE
Requires-Dist: faba (>=0.0.3)
Provides-Extra: tests
Requires-Dist: pytest ; extra == 'tests'
Requires-Dist: pytest-asyncio ; extra == 'tests'
